odoo/addons/project_analytic_code/README.rst
odoo/addons/project_analytic_code/__init__.py
odoo/addons/project_analytic_code/__manifest__.py
odoo/addons/project_analytic_code/i18n/fr.po
odoo/addons/project_analytic_code/i18n/it.po
odoo/addons/project_analytic_code/i18n/project_analytic_code.pot
odoo/addons/project_analytic_code/models/__init__.py
odoo/addons/project_analytic_code/models/project.py
odoo/addons/project_analytic_code/readme/CONTRIBUTORS.md
odoo/addons/project_analytic_code/readme/DESCRIPTION.md
odoo/addons/project_analytic_code/readme/USAGE.md
odoo/addons/project_analytic_code/static/description/icon.png
odoo/addons/project_analytic_code/static/description/index.html
odoo/addons/project_analytic_code/tests/__init__.py
odoo/addons/project_analytic_code/tests/test_project.py
odoo/addons/project_analytic_code/views/project.xml
odoo_addon_project_analytic_code-17.0.0.1.0.4.dist-info/METADATA
odoo_addon_project_analytic_code-17.0.0.1.0.4.dist-info/WHEEL
odoo_addon_project_analytic_code-17.0.0.1.0.4.dist-info/top_level.txt
odoo_addon_project_analytic_code-17.0.0.1.0.4.dist-info/RECORD
