Metadata-Version: 2.1
Name: odoo-addon-project_analytic_code
Version: 17.0.0.1.0.4
Requires-Python: >=3.10
Requires-Dist: odoo>=17.0a,<17.1dev
Summary: Search projects by analytic account code.
Home-page: https://github.com/OCA/project
License: AGPL-3
Author: Pierre Verkest, Odoo Community Association (OCA)
Author-email: support@odoo-community.org
Classifier: Programming Language :: Python
Classifier: Framework :: Odoo
Classifier: Framework :: Odoo :: 17.0
Classifier: License :: OSI Approved :: GNU Affero General Public License v3
